tsilva_notebook_utils/__init__.py
tsilva_notebook_utils/google_colab.py
tsilva_notebook_utils/notifications.py
tsilva_notebook_utils/video.py
tsilva_notebook_utils-0.1.9.dist-info/LICENSE
tsilva_notebook_utils-0.1.9.dist-info/METADATA
tsilva_notebook_utils-0.1.9.dist-info/WHEEL
tsilva_notebook_utils-0.1.9.dist-info/top_level.txt
tsilva_notebook_utils-0.1.9.dist-info/RECORD
